LICENSE
README.md
pyproject.toml
setup.py
analysis_runner/__init__.py
analysis_runner/_version.py
analysis_runner/cli.py
analysis_runner/cli_analysisrunner.py
analysis_runner/cli_config.py
analysis_runner/cli_cromwell.py
analysis_runner/cromwell.py
analysis_runner/dataproc.py
analysis_runner/util.py
analysis_runner.egg-info/PKG-INFO
analysis_runner.egg-info/SOURCES.txt
analysis_runner.egg-info/dependency_links.txt
analysis_runner.egg-info/entry_points.txt
analysis_runner.egg-info/not-zip-safe
analysis_runner.egg-info/requires.txt
analysis_runner.egg-info/top_level.txt
test/test_analysis_runner.py